README.rst
setup.py
covfefe/__init__.py
covfefe/covfefe.py
pycovfefe.egg-info/PKG-INFO
pycovfefe.egg-info/SOURCES.txt
pycovfefe.egg-info/dependency_links.txt
pycovfefe.egg-info/entry_points.txt
pycovfefe.egg-info/top_level.txt