Metadata-Version: 1.1
Name: pycovfefe
Version: 0.1a0
Summary: Python Interface for covfefe caliber content generation.
Home-page: https://bitbucket.org/petersanchez/pycovfefe/
Author: Peter Sanchez
Author-email: petersanchez@gmail.com
License: UNKNOWN
Platform: any
Classifier: Development Status :: 4 - Beta
Classifier: Intended Audience :: Developers
Classifier: Natural Language :: English
Classifier: Operating System :: OS Independent
Classifier: Programming Language :: Python
Classifier: Programming Language :: Python :: 2.7
